{
  "description": "Transform any subject into a stunning online course with LearningStudioAI. Our AI-powered authoring tool makes course creation effortless, so you can focus on what matters most - building engaging content. Enjoy seamless scaling across all devices, with magical-feeling features that delight learners. Already have your own platform? LearningStudioAI provides best-in-class quality of service learning analytics to help you optimize your teaching. Get started today and unleash the power of AI in education.",
  "title": "Create courses with AI-powered authoring tool | LearningStudioAI",
  "introduction": "Introducing LearningStudioAI, the next-gen online course creation tool",
  "features": [],
  "pricing": "",
  "faqs": [],
  "category": "Education",
  "url": "https://learningstudioai.com/"
}